PatchTool/__init__.py
PatchTool/acllm.py
PatchTool/func.py
PatchTool/llm.py
PatchTool/sos.py
ai_patch_tool-0.1.0.dist-info/METADATA
ai_patch_tool-0.1.0.dist-info/WHEEL
ai_patch_tool-0.1.0.dist-info/entry_points.txt
ai_patch_tool-0.1.0.dist-info/top_level.txt
ai_patch_tool-0.1.0.dist-info/RECORD
