Metadata-Version: 2.4
Name: ai-patch-tool
Version: 0.1.0
Summary: An AI-powered CLI tool to enhance your coding workflow by fixing errors, modifying code, adding comments, and generating files.
Home-page: https://github.com/aayush00700/Patcher
Author: Aayushman Katariya
Author-email: erenyeager545w@gmail.com
License: MIT
Project-URL: Bug Reports, https://github.com/aayush00700/Patcher/issues
Project-URL: Source, https://github.com/aayush00700/Patcher
Project-URL: Documentation, https://github.com/aayush00700/Patcher#readme
Keywords: ai,cli,code-fix,debugging,patch,automation,gemini,stack-overflow
Classifier: Development Status :: 3 - Alpha
Classifier: Intended Audience :: Developers
Classifier: Topic :: Software Development :: Code Generators
Classifier: Topic :: Software Development :: Debuggers
Classifier: License :: OSI Approved :: MIT License
Classifier: Programming Language :: Python :: 3
Classifier: Programming Language :: Python :: 3.7
Classifier: Programming Language :: Python :: 3.8
Classifier: Programming Language :: Python :: 3.9
Classifier: Programming Language :: Python :: 3.10
Classifier: Programming Language :: Python :: 3.11
Classifier: Programming Language :: Python :: 3.12
Classifier: Operating System :: OS Independent
Classifier: Environment :: Console
Requires-Python: >=3.7
Requires-Dist: typer
Requires-Dist: google-generativeai
Requires-Dist: requests
Requires-Dist: rich
Provides-Extra: dev
Requires-Dist: pytest; extra == "dev"
Requires-Dist: black; extra == "dev"
Requires-Dist: flake8; extra == "dev"
Requires-Dist: mypy; extra == "dev"
Provides-Extra: test
Requires-Dist: pytest; extra == "test"
Requires-Dist: pytest-cov; extra == "test"
Dynamic: author
Dynamic: author-email
Dynamic: classifier
Dynamic: description
Dynamic: description-content-type
Dynamic: home-page
Dynamic: keywords
Dynamic: license
Dynamic: project-url
Dynamic: provides-extra
Dynamic: requires-dist
Dynamic: requires-python
Dynamic: summary
